LICENSE
README.md
setup.py
print_rank_0/__init__.py
print_rank_0.egg-info/PKG-INFO
print_rank_0.egg-info/SOURCES.txt
print_rank_0.egg-info/dependency_links.txt
print_rank_0.egg-info/top_level.txt